odoo8_addon_inactive_session_timeout-8.0.1.0.0.99.dev10-py2.7-nspkg.pth
odoo8_addon_inactive_session_timeout-8.0.1.0.0.99.dev10.dist-info/DESCRIPTION.rst
odoo8_addon_inactive_session_timeout-8.0.1.0.0.99.dev10.dist-info/METADATA
odoo8_addon_inactive_session_timeout-8.0.1.0.0.99.dev10.dist-info/RECORD
odoo8_addon_inactive_session_timeout-8.0.1.0.0.99.dev10.dist-info/WHEEL
odoo8_addon_inactive_session_timeout-8.0.1.0.0.99.dev10.dist-info/metadata.json
odoo8_addon_inactive_session_timeout-8.0.1.0.0.99.dev10.dist-info/namespace_packages.txt
odoo8_addon_inactive_session_timeout-8.0.1.0.0.99.dev10.dist-info/top_level.txt
odoo_addons/inactive_session_timeout/README.rst
odoo_addons/inactive_session_timeout/__init__.py
odoo_addons/inactive_session_timeout/__openerp__.py
odoo_addons/inactive_session_timeout/data/ir_config_parameter_data.xml
odoo_addons/inactive_session_timeout/i18n/ar.po
odoo_addons/inactive_session_timeout/i18n/ca.po
odoo_addons/inactive_session_timeout/i18n/da.po
odoo_addons/inactive_session_timeout/i18n/de.po
odoo_addons/inactive_session_timeout/i18n/el_GR.po
odoo_addons/inactive_session_timeout/i18n/es.po
odoo_addons/inactive_session_timeout/i18n/es_ES.po
odoo_addons/inactive_session_timeout/i18n/fi.po
odoo_addons/inactive_session_timeout/i18n/fr.po
odoo_addons/inactive_session_timeout/i18n/fr_CH.po
odoo_addons/inactive_session_timeout/i18n/hr.po
odoo_addons/inactive_session_timeout/i18n/hr_HR.po
odoo_addons/inactive_session_timeout/i18n/inactive_session_timeout.pot
odoo_addons/inactive_session_timeout/i18n/it.po
odoo_addons/inactive_session_timeout/i18n/nl.po
odoo_addons/inactive_session_timeout/i18n/pt_BR.po
odoo_addons/inactive_session_timeout/i18n/sl.po
odoo_addons/inactive_session_timeout/i18n/tr.po
odoo_addons/inactive_session_timeout/i18n/tr_TR.po
odoo_addons/inactive_session_timeout/i18n/zh_CN.po
odoo_addons/inactive_session_timeout/models/__init__.py
odoo_addons/inactive_session_timeout/models/ir_config_parameter.py
odoo_addons/inactive_session_timeout/models/res_users.py
odoo_addons/inactive_session_timeout/static/description/icon.png
